restful_functions/__init__.py
restful_functions/_meta.py
restful_functions/manager.py
restful_functions/server.py
restful_functions/modules/__init__.py
restful_functions/modules/function.py
restful_functions/modules/process.py
restful_functions/modules/task.py
restful_functions/utils/__init__.py
restful_functions/utils/logger.py
restful_functions-2.0.1.dist-info/LICENSE.txt
restful_functions-2.0.1.dist-info/METADATA
restful_functions-2.0.1.dist-info/WHEEL
restful_functions-2.0.1.dist-info/top_level.txt
restful_functions-2.0.1.dist-info/RECORD
